forebodere/__init__.py
forebodere/__main__.py
forebodere/bot.py
forebodere/buffer.py
forebodere/cli.py
forebodere/models.py
forebodere/register.py
forebodere-0.1.0.dist-info/LICENSE
forebodere-0.1.0.dist-info/METADATA
forebodere-0.1.0.dist-info/WHEEL
forebodere-0.1.0.dist-info/dependency_links.txt
forebodere-0.1.0.dist-info/entry_points.txt
forebodere-0.1.0.dist-info/top_level.txt
forebodere-0.1.0.dist-info/RECORD
