Metadata-Version: 2.1
Name: forebodere
Version: 0.1.0
Summary: Discord quote bot
Home-page: UNKNOWN
Author: Mika Naylor (Autophagy)
Author-email: mail@autophagy.io
License: UNKNOWN
Platform: UNKNOWN
Classifier: Development Status :: 4 - Beta
Classifier: License :: OSI Approved :: MIT License
Classifier: Programming Language :: Python :: 3
Classifier: Programming Language :: Python :: 3.6
Classifier: Programming Language :: Python :: 3.7
Requires-Python: >=3.6
Requires-Dist: Whoosh (==2.7.4)
Requires-Dist: wisdomhord (==0.3.1)
Requires-Dist: discord.py (==1.0.0a1590+g860d6a9)
Requires-Dist: markovify (==0.7.1)
